README.md
setup.py
AliFCWeb/__init__.py
AliFCWeb/config_center.py
AliFCWeb/connect.py
AliFCWeb/constant.py
AliFCWeb/fcweb.py
AliFCWeb/response.py
AliFCWeb/right.py
AliFCWeb/utils.py
AliFCWeb.egg-info/PKG-INFO
AliFCWeb.egg-info/SOURCES.txt
AliFCWeb.egg-info/dependency_links.txt
AliFCWeb.egg-info/top_level.txt
AliFCWeb/engine/PooledDB.py
AliFCWeb/engine/Pools.py
AliFCWeb/engine/SteadyDB.py
AliFCWeb/engine/__init__.py
AliFCWeb/fcorm/__init__.py
AliFCWeb/fcorm/constant.py
AliFCWeb/fcorm/db_common.py
AliFCWeb/fcorm/example.py
AliFCWeb/fcorm/orm.py
AliFCWeb/fcutils/__init__.py
AliFCWeb/fcutils/acs_utils.py
AliFCWeb/fcutils/conf_utils.py
AliFCWeb/fcutils/dict2xml.py
AliFCWeb/fcutils/http_utils.py
AliFCWeb/fcutils/jwt_utils.py
AliFCWeb/fcutils/oss_utils.py
AliFCWeb/fcutils/pwd_utils.py
AliFCWeb/fcutils/sql_utils.py
AliFCWeb/fcutils/xml2dict.py
AliFCWeb/sign/__init__.py
AliFCWeb/sign/mysql_sign.py
AliFCWeb/sign/postgre_sql_sign.py
AliFCWeb/sign/redis_sign.py
AliFCWeb/sign/sign.py