Metadata-Version: 1.0
Name: AliFCWeb
Version: 1.1.0
Summary: 阿里云函数计算web框架
Home-page: https://github.com/xingluoxingkong/ali-fc-web.git
Author: 星泪
Author-email: xlxk@xlxk.top
License: MIT Licence
Keywords: pip,pathtool,timetool,magetool,mage
Platform: any
